time_profiler/__init__.py
time_profiler/logger.py
time_profiler/utils.py
time_profiler/version.py
time_profiler-0.0.2.dist-info/WHEEL
time_profiler-0.0.2.dist-info/METADATA
time_profiler-0.0.2.dist-info/RECORD
