Metadata-Version: 2.1
Name: time-profiler
Version: 0.0.2
Summary: This project provides a method for determining how long it takes a function to complete its execution.
Home-page: https://github.com/harerakalex/timer
License: MIT
Author: harerakalex
Author-email: hareraloston@gmail.com
Requires-Python: >=3.8,<4.0
Classifier: License :: OSI Approved :: MIT License
Classifier: Programming Language :: Python :: 3
Classifier: Programming Language :: Python :: 3.10
Classifier: Programming Language :: Python :: 3.8
Classifier: Programming Language :: Python :: 3.9
Project-URL: Repository, https://github.com/harerakalex/timer
